ENSCardMaker/ENSCardMaker.py
ENSCardMaker/__init__.py
ENSCardMaker/__main__.py
ENSCardMaker/fonts/Inter-Bold.ttf
ENSCardMaker/fonts/Inter-Regular.ttf
ENSCardMaker-1.2.2.dist-info/METADATA
ENSCardMaker-1.2.2.dist-info/WHEEL
ENSCardMaker-1.2.2.dist-info/entry_points.txt
ENSCardMaker-1.2.2.dist-info/top_level.txt
ENSCardMaker-1.2.2.dist-info/RECORD
