Metadata-Version: 2.1
Name: ENSCardMaker
Version: 1.2.2
Summary: Takes an ENS name or ETH address and returns a card based on information from an ENS profile.
Author: LittleBit
Author-email: littlebit@littlebitstudios.com
License: MIT
Classifier: License :: OSI Approved :: MIT License
Classifier: Operating System :: OS Independent
Requires-Dist: requests
Requires-Dist: Pillow
Requires-Dist: pydenticon
